subnet/agent_pb2.pyi
subnet/bid_pb2.pyi
subnet/checkpoint_pb2.pyi
subnet/execution_report_pb2.pyi
subnet/matcher_pb2.pyi
subnet/matcher_service_pb2.pyi
subnet/registry_service_pb2.pyi
subnet/report_pb2.pyi
subnet/service_pb2.pyi
subnet/validation_pb2.pyi
subnet/validator_pb2.pyi
subnet_sdk/__init__.py
subnet_sdk/config_builder.py
subnet_sdk/grpc_transport.py
subnet_sdk/matcher_client.py
subnet_sdk/sdk.py
subnet_sdk/types.py
subnet_sdk/proto/__init__.py
subnet_sdk/proto/subnet/agent_pb2.py
subnet_sdk/proto/subnet/agent_pb2_grpc.py
subnet_sdk/proto/subnet/bid_pb2.py
subnet_sdk/proto/subnet/bid_pb2_grpc.py
subnet_sdk/proto/subnet/checkpoint_pb2.py
subnet_sdk/proto/subnet/checkpoint_pb2_grpc.py
subnet_sdk/proto/subnet/execution_report_pb2.py
subnet_sdk/proto/subnet/execution_report_pb2_grpc.py
subnet_sdk/proto/subnet/matcher_pb2.py
subnet_sdk/proto/subnet/matcher_pb2_grpc.py
subnet_sdk/proto/subnet/matcher_service_pb2.py
subnet_sdk/proto/subnet/matcher_service_pb2_grpc.py
subnet_sdk/proto/subnet/report_pb2.py
subnet_sdk/proto/subnet/report_pb2_grpc.py
subnet_sdk/proto/subnet/service_pb2.py
subnet_sdk/proto/subnet/service_pb2_grpc.py
subnet_sdk/proto/subnet/validation_pb2.py
subnet_sdk/proto/subnet/validation_pb2_grpc.py
subnet_sdk/proto/subnet/validator_pb2.py
subnet_sdk/proto/subnet/validator_pb2_grpc.py
subnet_sdk-0.1.0.dist-info/METADATA
subnet_sdk-0.1.0.dist-info/WHEEL
subnet_sdk-0.1.0.dist-info/top_level.txt
subnet_sdk-0.1.0.dist-info/RECORD
