Metadata-Version: 2.4
Name: subnet-sdk
Version: 0.1.0
Summary: Python SDK for Subnet Agent Development
Home-page: https://github.com/PIN-AI/subnet-sdk
Author: PinAI
Author-email: PinAI <dev@pinai.io>
Project-URL: Homepage, https://github.com/PIN-AI/subnet-sdk
Project-URL: Documentation, https://github.com/PIN-AI/subnet-sdk/tree/main/python
Project-URL: Repository, https://github.com/PIN-AI/subnet-sdk
Project-URL: Issues, https://github.com/PIN-AI/subnet-sdk/issues
Classifier: Development Status :: 3 - Alpha
Classifier: Intended Audience :: Developers
Classifier: Topic :: Software Development :: Libraries :: Python Modules
Classifier: License :: OSI Approved :: MIT License
Classifier: Programming Language :: Python :: 3
Classifier: Programming Language :: Python :: 3.8
Classifier: Programming Language :: Python :: 3.9
Classifier: Programming Language :: Python :: 3.10
Classifier: Programming Language :: Python :: 3.11
Classifier: Programming Language :: Python :: 3.12
Requires-Python: >=3.8
Requires-Dist: grpcio>=1.50.0
Requires-Dist: grpcio-tools>=1.50.0
Requires-Dist: protobuf>=4.21.0
Requires-Dist: cryptography>=41.0.0
Requires-Dist: eth-account>=0.9.0
Requires-Dist: web3>=6.0.0
Requires-Dist: aiohttp>=3.9.0
Provides-Extra: dev
Requires-Dist: pytest>=7.0.0; extra == "dev"
Requires-Dist: pytest-asyncio>=0.21.0; extra == "dev"
Requires-Dist: pytest-cov>=4.0.0; extra == "dev"
Requires-Dist: black>=23.0.0; extra == "dev"
Requires-Dist: flake8>=6.0.0; extra == "dev"
Requires-Dist: mypy>=1.0.0; extra == "dev"
Dynamic: author
Dynamic: home-page
Dynamic: requires-python
